LICENSE
MANIFEST.in
readme.md
setup.py
version.txt
nezha_exporter/__init__.py
nezha_exporter/api.py
nezha_exporter.egg-info/PKG-INFO
nezha_exporter.egg-info/SOURCES.txt
nezha_exporter.egg-info/dependency_links.txt
nezha_exporter.egg-info/entry_points.txt
nezha_exporter.egg-info/requires.txt
nezha_exporter.egg-info/top_level.txt