Metadata-Version: 2.1
Name: nezha-exporter
Version: 0.1
Summary: nezha 面板 api 转 prometheus metrics 接口
Home-page: https://github.com/aitsc/nezha-exporter
Author: aitsc
Requires-Python: >=3.7
License-File: LICENSE
